[
    {
      "id": 1,
      "price": 3.50,
      "username": "coffeeLover",
      "category": "Espresso",
      "productname": "Espresso Single",
      "quantity": 2
    },
    {
      "id": 2,
      "price": 4.20,
      "username": "javaFan",
      "category": "Latte",
      "productname": "Vanilla Latte",
      "quantity": 1
    },
    {
      "id": 3,
      "price": 2.80,
      "username": "beanMaster",
      "category": "Cappuccino",
      "productname": "Classic Cappuccino",
      "quantity": 3
    },
    {
      "id": 4,
      "price": 3.00,
      "username": "mochaAddict",
      "category": "Mocha",
      "productname": "Chocolate Mocha",
      "quantity": 2
    },
    {
      "id": 5,
      "price": 3.80,
      "username": "brewMaster",
      "category": "Americano",
      "productname": "Black Americano",
      "quantity": 1
    },
    {
      "id": 6,
      "price": 3.20,
      "username": "espressoFan",
      "category": "Espresso",
      "productname": "Double Espresso",
      "quantity": 2
    },
    {
      "id": 7,
      "price": 4.50,
      "username": "latteLover",
      "category": "Latte",
      "productname": "Caramel Latte",
      "quantity": 1
    },
    {
      "id": 8,
      "price": 3.00,
      "username": "cappuccinoKing",
      "category": "Cappuccino",
      "productname": "Hazelnut Cappuccino",
      "quantity": 2
    },
    {
      "id": 9,
      "price": 3.80,
      "username": "mochaMania",
      "category": "Mocha",
      "productname": "White Chocolate Mocha",
      "quantity": 1
    },
    {
      "id": 10,
      "price": 3.50,
      "username": "americanoAddict",
      "category": "Americano",
      "productname": "Mint Americano",
      "quantity": 2
    },
    {
      "id": 11,
      "price": 4.20,
      "username": "latteLady",
      "category": "Latte",
      "productname": "Pumpkin Spice Latte",
      "quantity": 1
    },
    {
      "id": 12,
      "price": 2.80,
      "username": "espressoEnthusiast",
      "category": "Espresso",
      "productname": "Macchiato",
      "quantity": 3
    },
    {
      "id": 13,
      "price": 3.00,
      "username": "cappuccinoQueen",
      "category": "Cappuccino",
      "productname": "Vanilla Cappuccino",
      "quantity": 2
    },
    {
      "id": 14,
      "price": 3.80,
      "username": "mochaMistress",
      "category": "Mocha",
      "productname": "Cinnamon Mocha",
      "quantity": 1
    },
    {
      "id": 15,
      "price": 3.20,
      "username": "espressoExpert",
      "category": "Espresso",
      "productname": "Ristretto",
      "quantity": 2
    },
    {
      "id": 16,
      "price": 4.50,
      "username": "latteLord",
      "category": "Latte",
      "productname": "Coconut Latte",
      "quantity": 1
    },
    {
      "id": 17,
      "price": 3.00,
      "username": "cappuccinoConnoisseur",
      "category": "Cappuccino",
      "productname": "Irish Cream Cappuccino",
      "quantity": 2
    },
    {
      "id": 18,
      "price": 3.80,
      "username": "mochaMaster",
      "category": "Mocha",
      "productname": "Salted Caramel Mocha",
      "quantity": 1
    },
    {
      "id": 19,
      "price": 3.50,
      "username": "americanoAficionado",
      "category": "Americano",
      "productname": "Espresso Americano",
      "quantity": 2
    },
    {
      "id": 20,
      "price": 4.20,
      "username": "latteLad",
      "category": "Latte",
      "productname": "Honey Lavender Latte",
      "quantity": 1
    },
    {
      "id": 21,
      "price": 2.80,
      "username": "espressoExplorer",
      "category": "Espresso",
      "productname": "Affogato",
      "quantity": 3
    },
    {
      "id": 22,
      "price": 3.00,
      "username": "cappuccinoChampion",
      "category": "Cappuccino",
      "productname": "Almond Cappuccino",
      "quantity": 2
    },
    {
      "id": 23,
      "price": 3.80,
      "username": "mochaMadness",
      "category": "Mocha",
      "productname": "Peppermint Mocha",
      "quantity": 1
    },
    {
      "id": 24,
      "price": 3.20,
      "username": "espressoEnthusiast",
      "category": "Espresso",
      "productname": "Flat White",
      "quantity": 2
    },
    {
      "id": 25,
      "price": 4.50,
      "username": "latteLover",
      "category": "Latte",
      "productname": "Maple Pecan Latte",
      "quantity": 1
    }
  ]
  